<annotation>
	<folder>image20180130163901154PCBcut</folder>
	<filename>20180130163901154PCB112.jpg</filename>
	<path>D:\project\image20180130163901154PCBcut\20180130163901154PCB112.jpg</path>
	<source>
		<database>Unknown</database>
	</source>
	<size>
		<width>416</width>
		<height>416</height>
		<depth>3</depth>
	</size>
	<segmented>0</segmented>
	<object>
		<name>spot</name>
		<pose>Unspecified</pose>
		<truncated>0</truncated>
		<difficult>0</difficult>
		<bndbox>
			<xmin>129</xmin>
			<ymin>320</ymin>
			<xmax>213</xmax>
			<ymax>403</ymax>
		</bndbox>
	</object>
	<object>
		<name>spot</name>
		<pose>Unspecified</pose>
		<truncated>0</truncated>
		<difficult>0</difficult>
		<bndbox>
			<xmin>156</xmin>
			<ymin>143</ymin>
			<xmax>251</xmax>
			<ymax>234</ymax>
		</bndbox>
	</object>
	<object>
		<name>spot</name>
		<pose>Unspecified</pose>
		<truncated>0</truncated>
		<difficult>0</difficult>
		<bndbox>
			<xmin>268</xmin>
			<ymin>104</ymin>
			<xmax>329</xmax>
			<ymax>167</ymax>
		</bndbox>
	</object>
</annotation>
