<annotation>
	<folder>images20180118080921508PCBcut</folder>
	<filename>20180118080921508PCB33.jpg</filename>
	<path>C:\Users\10045\Desktop\images\images20180118080921508PCBcut\20180118080921508PCB33.jpg</path>
	<source>
		<database>Unknown</database>
	</source>
	<size>
		<width>416</width>
		<height>416</height>
		<depth>3</depth>
	</size>
	<segmented>0</segmented>
	<object>
		<name>spot</name>
		<pose>Unspecified</pose>
		<truncated>1</truncated>
		<difficult>0</difficult>
		<bndbox>
			<xmin>1</xmin>
			<ymin>137</ymin>
			<xmax>36</xmax>
			<ymax>201</ymax>
		</bndbox>
	</object>
	<object>
		<name>spot</name>
		<pose>Unspecified</pose>
		<truncated>0</truncated>
		<difficult>0</difficult>
		<bndbox>
			<xmin>68</xmin>
			<ymin>138</ymin>
			<xmax>124</xmax>
			<ymax>195</ymax>
		</bndbox>
	</object>
	<object>
		<name>spot</name>
		<pose>Unspecified</pose>
		<truncated>0</truncated>
		<difficult>0</difficult>
		<bndbox>
			<xmin>191</xmin>
			<ymin>180</ymin>
			<xmax>262</xmax>
			<ymax>241</ymax>
		</bndbox>
	</object>
	<object>
		<name>spot</name>
		<pose>Unspecified</pose>
		<truncated>0</truncated>
		<difficult>0</difficult>
		<bndbox>
			<xmin>324</xmin>
			<ymin>139</ymin>
			<xmax>382</xmax>
			<ymax>195</ymax>
		</bndbox>
	</object>
	<object>
		<name>spot</name>
		<pose>Unspecified</pose>
		<truncated>0</truncated>
		<difficult>0</difficult>
		<bndbox>
			<xmin>358</xmin>
			<ymin>370</ymin>
			<xmax>409</xmax>
			<ymax>409</ymax>
		</bndbox>
	</object>
</annotation>
