<annotation>
	<folder>image20180130163901154PCBcut</folder>
	<filename>20180130163901154PCB125.jpg</filename>
	<path>D:\project\image20180130163901154PCBcut\20180130163901154PCB125.jpg</path>
	<source>
		<database>Unknown</database>
	</source>
	<size>
		<width>416</width>
		<height>416</height>
		<depth>3</depth>
	</size>
	<segmented>0</segmented>
	<object>
		<name>spot</name>
		<pose>Unspecified</pose>
		<truncated>0</truncated>
		<difficult>0</difficult>
		<bndbox>
			<xmin>246</xmin>
			<ymin>55</ymin>
			<xmax>330</xmax>
			<ymax>141</ymax>
		</bndbox>
	</object>
	<object>
		<name>spot</name>
		<pose>Unspecified</pose>
		<truncated>0</truncated>
		<difficult>0</difficult>
		<bndbox>
			<xmin>219</xmin>
			<ymin>185</ymin>
			<xmax>341</xmax>
			<ymax>310</ymax>
		</bndbox>
	</object>
</annotation>
